langpeek/__init__.py
langpeek/langpeek.py
langpeek/data/stopwords.yaml
langpeek-0.1.0.dist-info/METADATA
langpeek-0.1.0.dist-info/WHEEL
langpeek-0.1.0.dist-info/top_level.txt
langpeek-0.1.0.dist-info/RECORD
